{
    "pools": [
        {
            "rolls": 1,
            "entries": [
                {
                    "type": "minecraft:loot_table",
                    "name": "vacuumhoppers:vacuum_hopper_tier_1"
                }
            ]
        },
        {
            "rolls": 1,
            "entries": [
                {
                    "type": "minecraft:item",
                    "name": "minecraft:emerald",
                    "functions": [
                        {
                            "function": "minecraft:set_count",
                            "count": 2
                        }
                    ]
                }
            ]
        },
        {
            "rolls": 1,
            "entries": [
                {
                    "type": "minecraft:item",
                    "name": "minecraft:quartz_block",
                    "functions": [
                        {
                            "function": "minecraft:set_count",
                            "count": 2
                        }
                    ]
                }
            ]
        },
        {
            "rolls": 1,
            "entries": [
                {
                    "type": "minecraft:item",
                    "name": "minecraft:ender_eye",
                    "functions": [
                        {
                            "function": "minecraft:set_count",
                            "count": 1
                        }
                    ]
                }
            ]
        }
    ]
}